json_indent/__init__.py
json_indent/__main__.py
json_indent/completion.py
json_indent/iofile.py
json_indent/json_indent.py
json_indent/pyversion.py
json_indent/util.py
json_indent-2.7.5.dist-info/METADATA
json_indent-2.7.5.dist-info/WHEEL
json_indent-2.7.5.dist-info/entry_points.txt
json_indent-2.7.5.dist-info/licenses/LICENSE
json_indent-2.7.5.dist-info/RECORD
