Metadata-Version: 2.3
Name: json-indent
Version: 2.7.5
Summary: Simple Python-based JSON parser/indenter/formatter
Project-URL: Repository, https://github.com/jmknoble/json-indent
Author-email: jmknoble <jmknoble@pobox.com>
License: MIT License
Keywords: cli,indent,json,pre-commit,reformat
Classifier: Development Status :: 5 - Production/Stable
Classifier: Environment :: Console
Classifier: Environment :: Other Environment
Classifier: Intended Audience :: Developers
Classifier: Intended Audience :: Information Technology
Classifier: License :: OSI Approved :: MIT License
Classifier: Operating System :: OS Independent
Classifier: Programming Language :: Python :: 3
Classifier: Programming Language :: Python :: 3.10
Classifier: Programming Language :: Python :: 3.11
Classifier: Topic :: File Formats :: JSON
Classifier: Topic :: Software Development
Classifier: Topic :: Utilities
Requires-Python: >=3.10
Requires-Dist: argcomplete>=1.12.3
